<?xml version="1.0" ?>
<root>
	<dynamicobstacles>
		<defaultparameters size="0.5"/>
		<obstacle id="0" size="3.2">
			<action id="0" x0="247" y0="295" xf="256" yf="195" duration="5"/>
		</obstacle>
		<obstacle id="1" size="3.3">
			<action id="0" x0="282" y0="336" xf="278" yf="339" duration="5"/>
		</obstacle>
		<obstacle id="2" size="4.5">
			<action id="0" x0="309" y0="266" xf="314" yf="263" duration="5"/>
		</obstacle>
		<obstacle id="3" size="3.0">
			<action id="0" x0="297" y0="324" xf="272" yf="358" duration="5"/>
		</obstacle>
		<obstacle id="4" size="3.1">
			<action id="0" x0="325" y0="364" xf="312" yf="371" duration="5"/>
		</obstacle>
	</dynamicobstacles>
</root>